LICENSE
README.md
setup.cfg
setup.py
src/pyngres/IIAPI_CONSTANTS.py
src/pyngres/IIAPI_PARM.py
src/pyngres/__init__.py
src/pyngres/asyncio.py
src/pyngres/blocking.py
src/pyngres/pyngres.py
src/pyngres.egg-info/PKG-INFO
src/pyngres.egg-info/SOURCES.txt
src/pyngres.egg-info/dependency_links.txt
src/pyngres.egg-info/requires.txt
src/pyngres.egg-info/top_level.txt