Metadata-Version: 2.2
Name: pyngres
Version: 0.5.0
Summary: Python bindings for Actian Ingres/Vector/X OpenAPI
Home-page: https://github.com/quelgeek/pyngres
Author: Roy Hann
Author-email: roy.hann@rationalcommerce.com
License: MIT
Keywords: Ingres,Actian,HCL-Software
License-File: LICENSE
Requires-Dist: loguru
